m2m/__init__.py
m2m/config.py
m2m/http2influx.py
m2m/meteofrance2mqtt.py
m2m/mqtt2influx.py
m2m/path.py
m2m-0.4.0.data/scripts/http2influx
m2m-0.4.0.dist-info/AUTHORS
m2m-0.4.0.dist-info/LICENSE
m2m-0.4.0.dist-info/METADATA
m2m-0.4.0.dist-info/WHEEL
m2m-0.4.0.dist-info/entry_points.txt
m2m-0.4.0.dist-info/top_level.txt
m2m-0.4.0.dist-info/RECORD
