Metadata-Version: 2.1
Name: m2m
Version: 0.4.0
Summary: M2M Daemons.
Author-email: Jérémie DECOCK <jd.jdhp@gmail.com>
Classifier: Development Status :: 4 - Beta
Classifier: Intended Audience :: Developers
Classifier: Natural Language :: English
Classifier: Operating System :: OS Independent
Classifier: Programming Language :: Python :: 3
Classifier: Topic :: Software Development :: Libraries
Requires-Python: >=3.8
License-File: LICENSE
License-File: AUTHORS
Requires-Dist: Flask
Requires-Dist: influxdb-client
Requires-Dist: paho-mqtt >=2.1.0
Requires-Dist: pyyaml
Requires-Dist: requests-html
Requires-Dist: waitress
